hebill_functions/__init__.py
hebill_functions/file/__init__.py
hebill_functions/file/import_dict_from_ini_file.py
hebill_functions/file/import_dict_from_py_file.py
hebill_functions-1.0.3.dist-info/METADATA
hebill_functions-1.0.3.dist-info/WHEEL
hebill_functions-1.0.3.dist-info/top_level.txt
hebill_functions-1.0.3.dist-info/RECORD
