Metadata-Version: 2.1
Name: hebill-functions
Version: 1.0.3
Summary: Python Basic functions
Home-page: https://www.hebill.net/he_functions
Author: He Bill
Author-email: hebill@me.com
Requires-Python: >=3.11
